MANIFEST.in
README.txt
setup.py
docs/HISTORY.txt
src/zeam/__init__.py
src/zeam.form.layout.egg-info/PKG-INFO
src/zeam.form.layout.egg-info/SOURCES.txt
src/zeam.form.layout.egg-info/dependency_links.txt
src/zeam.form.layout.egg-info/namespace_packages.txt
src/zeam.form.layout.egg-info/not-zip-safe
src/zeam.form.layout.egg-info/requires.txt
src/zeam.form.layout.egg-info/top_level.txt
src/zeam/form/__init__.py
src/zeam/form/layout/__init__.py
src/zeam/form/layout/configure.zcml
src/zeam/form/layout/form.py
src/zeam/form/layout/ftesting.zcml
src/zeam/form/layout/testing.py
src/zeam/form/layout/form_templates/composedformtemplate.cpt
src/zeam/form/layout/form_templates/formtemplate.cpt
src/zeam/form/layout/ftests/__init__.py
src/zeam/form/layout/ftests/test_layout.py
src/zeam/form/layout/ftests/layout/__init__.py
src/zeam/form/layout/ftests/layout/composed.py
src/zeam/form/layout/ftests/layout/form.py
src/zeam/form/layout/ftests/layout/composed_templates/worldlayout.pt
src/zeam/form/layout/ftests/layout/form_templates/guylayout.pt
src/zeam/form/layout/tests/__init__.py
src/zeam/form/layout/tests/forms.txt
src/zeam/form/layout/tests/test_doctest.py