Metadata-Version: 1.0
Name: zeam.form.layout
Version: 0.3
Summary: megrok.layout support for zeam.form
Home-page: UNKNOWN
Author: Sylvain Viollon
Author-email: thefunny@gmail.com
License: BSD
Keywords: zeam form layout
Platform: UNKNOWN
Classifier: Framework :: Zope3
Classifier: Programming Language :: Python
Classifier: Programming Language :: Zope
Classifier: Intended Audience :: Developers
Classifier: Topic :: Software Development :: Libraries :: Python Modules
